nordlys/__init__.py
nordlys/clustering/__init__.py
nordlys/clustering/agglomerative.py
nordlys/clustering/base.py
nordlys/clustering/gmm.py
nordlys/clustering/hdbscan_clusterer.py
nordlys/clustering/kmeans.py
nordlys/clustering/metrics.py
nordlys/clustering/spectral.py
nordlys/clustering/sweep.py
nordlys/nordlys.py
nordlys/py.typed
nordlys/reduction/__init__.py
nordlys/reduction/base.py
nordlys/reduction/pca.py
nordlys/reduction/umap_reducer.py
nordlys-0.2.7.dist-info/WHEEL
nordlys-0.2.7.dist-info/METADATA
nordlys-0.2.7.dist-info/RECORD
