Metadata-Version: 2.4
Name: nordlys
Version: 0.2.7
Summary: Intelligent LLM Infrastructure with Smart Model Selection
Keywords: llm,ai,model-selection,machine-learning,nordlys
Author: Botir Khaltaev
Author-email: Botir Khaltaev <botirkhaltaev@llmadaptive.uk>
License-Expression: MIT
Classifier: Development Status :: 3 - Alpha
Classifier: Intended Audience :: Developers
Classifier: License :: OSI Approved :: MIT License
Classifier: Operating System :: OS Independent
Classifier: Programming Language :: Python :: 3
Classifier: Programming Language :: Python :: 3.11
Classifier: Programming Language :: Python :: 3.12
Classifier: Topic :: Scientific/Engineering :: Artificial Intelligence
Classifier: Topic :: Software Development :: Libraries :: Python Modules
Classifier: Typing :: Typed
Requires-Dist: pydantic>=2.11.5,<3
Requires-Dist: pandas>=2.0.0
Requires-Dist: scikit-learn>=1.5.0,<2.0.0
Requires-Dist: hdbscan>=0.8.33
Requires-Dist: umap-learn>=0.5.0
Requires-Dist: numba>=0.56.0
Requires-Dist: cachetools>=5.0.0,<6
Requires-Dist: nordlys-core>=0.2.8,<1 ; extra == 'cpu'
Requires-Dist: torch>=2.2.0 ; extra == 'cpu'
Requires-Dist: sentence-transformers>=5.2.0,<6 ; extra == 'cpu'
Requires-Dist: nordlys-core-cu12>=0.2.8,<1 ; sys_platform == 'linux' and extra == 'cu12'
Requires-Dist: torch>=2.2.0 ; extra == 'cu12'
Requires-Dist: sentence-transformers>=5.2.0,<6 ; extra == 'cu12'
Requires-Python: >=3.11, <4.0
Project-URL: Homepage, https://www.nordlyslabs.com
Project-URL: Repository, https://github.com/Nordlys-Labs/nordlys
Project-URL: Documentation, https://docs.nordlyslabs.com
Project-URL: Bug Tracker, https://github.com/Nordlys-Labs/nordlys/issues
Provides-Extra: cpu
Provides-Extra: cu12
